odoo8_addon_stock_picking_invoicing_incoterm-8.0.1.0.0.99.dev18-py2.7-nspkg.pth
odoo8_addon_stock_picking_invoicing_incoterm-8.0.1.0.0.99.dev18.dist-info/DESCRIPTION.rst
odoo8_addon_stock_picking_invoicing_incoterm-8.0.1.0.0.99.dev18.dist-info/METADATA
odoo8_addon_stock_picking_invoicing_incoterm-8.0.1.0.0.99.dev18.dist-info/RECORD
odoo8_addon_stock_picking_invoicing_incoterm-8.0.1.0.0.99.dev18.dist-info/WHEEL
odoo8_addon_stock_picking_invoicing_incoterm-8.0.1.0.0.99.dev18.dist-info/metadata.json
odoo8_addon_stock_picking_invoicing_incoterm-8.0.1.0.0.99.dev18.dist-info/namespace_packages.txt
odoo8_addon_stock_picking_invoicing_incoterm-8.0.1.0.0.99.dev18.dist-info/top_level.txt
odoo_addons/stock_picking_invoicing_incoterm/README.rst
odoo_addons/stock_picking_invoicing_incoterm/__init__.py
odoo_addons/stock_picking_invoicing_incoterm/__openerp__.py
odoo_addons/stock_picking_invoicing_incoterm/i18n/ar.po
odoo_addons/stock_picking_invoicing_incoterm/i18n/bg.po
odoo_addons/stock_picking_invoicing_incoterm/i18n/bs.po
odoo_addons/stock_picking_invoicing_incoterm/i18n/ca.po
odoo_addons/stock_picking_invoicing_incoterm/i18n/cs.po
odoo_addons/stock_picking_invoicing_incoterm/i18n/de.po
odoo_addons/stock_picking_invoicing_incoterm/i18n/el_GR.po
odoo_addons/stock_picking_invoicing_incoterm/i18n/en_GB.po
odoo_addons/stock_picking_invoicing_incoterm/i18n/es.po
odoo_addons/stock_picking_invoicing_incoterm/i18n/es_AR.po
odoo_addons/stock_picking_invoicing_incoterm/i18n/es_CR.po
odoo_addons/stock_picking_invoicing_incoterm/i18n/es_EC.po
odoo_addons/stock_picking_invoicing_incoterm/i18n/es_MX.po
odoo_addons/stock_picking_invoicing_incoterm/i18n/es_PE.po
odoo_addons/stock_picking_invoicing_incoterm/i18n/et.po
odoo_addons/stock_picking_invoicing_incoterm/i18n/fi.po
odoo_addons/stock_picking_invoicing_incoterm/i18n/fr.po
odoo_addons/stock_picking_invoicing_incoterm/i18n/fr_CA.po
odoo_addons/stock_picking_invoicing_incoterm/i18n/fr_CH.po
odoo_addons/stock_picking_invoicing_incoterm/i18n/gl.po
odoo_addons/stock_picking_invoicing_incoterm/i18n/hr.po
odoo_addons/stock_picking_invoicing_incoterm/i18n/hr_HR.po
odoo_addons/stock_picking_invoicing_incoterm/i18n/hu.po
odoo_addons/stock_picking_invoicing_incoterm/i18n/id.po
odoo_addons/stock_picking_invoicing_incoterm/i18n/it.po
odoo_addons/stock_picking_invoicing_incoterm/i18n/ja.po
odoo_addons/stock_picking_invoicing_incoterm/i18n/lt.po
odoo_addons/stock_picking_invoicing_incoterm/i18n/mk.po
odoo_addons/stock_picking_invoicing_incoterm/i18n/mn.po
odoo_addons/stock_picking_invoicing_incoterm/i18n/nb.po
